gymconnectx/__init__.py
gymconnectx/envs/__init__.py
gymconnectx/envs/gymconnectxenv.py
gymconnectx-2.0.0.dist-info/LICENSE.md
gymconnectx-2.0.0.dist-info/METADATA
gymconnectx-2.0.0.dist-info/WHEEL
gymconnectx-2.0.0.dist-info/top_level.txt
gymconnectx-2.0.0.dist-info/RECORD
