Metadata-Version: 2.1
Name: gymconnectx
Version: 2.0.0
Summary: An OpenAI Gymnasium Environment Connect X Game with GUI. ConnectX is a game for two players that is based on the well-known Connect 4. The goal is to place X coins in a row, column, or diagonal on a board with dimensions M by N.
Home-page: https://github.com/fauzisho/GymConnectX
Author: Fauzi Sholichin
License: MIT License
Project-URL: Homepage, https://github.com/fauzisho/GymConnectX
Keywords: connect4,gymnasium,pygame,reinforcement learning
Classifier: License :: OSI Approved :: MIT License
Classifier: Programming Language :: Python
Classifier: Programming Language :: Python :: 3
Requires-Python: >=3.9
License-File: LICENSE.md
Requires-Dist: gymnasium
Requires-Dist: pygame
